sqlbear/__init__.py
sqlbear/_version.py
sqlbear/bson_connector.py
sqlbear/core.py
sqlbear/sql_helpers.py
sqlbear-1.0.0.dist-info/licenses/LICENSE
sqlbear-1.0.0.dist-info/METADATA
sqlbear-1.0.0.dist-info/WHEEL
sqlbear-1.0.0.dist-info/top_level.txt
sqlbear-1.0.0.dist-info/RECORD
