Metadata-Version: 2.4
Name: sqlbear
Version: 1.0.0
Summary: Wrapper for sqlalchemy engine that provides functions for handoff with pandas
Home-page: https://github.com/readytowin2298/sqlbear
Author: Your Name
Author-email: David Ames <readytowin2298@gmail.com>
License: MIT License
Project-URL: Homepage, https://github.com/readytowin2298/sqlbear
Project-URL: Repository, https://github.com/readytowin2298/sqlbear
Project-URL: Issues, https://github.com/readytowin2298/sqlbear/issues
Classifier: Programming Language :: Python :: 3
Classifier: License :: OSI Approved :: MIT License
Classifier: Operating System :: OS Independent
Requires-Python: >=3.7
License-File: LICENSE
Requires-Dist: pandas>=1.2
Requires-Dist: sqlalchemy>=1.4
Requires-Dist: pytz>=2025
Dynamic: author
Dynamic: classifier
Dynamic: home-page
Dynamic: license-file
Dynamic: requires-python
